passagemath_plot/__init__.py
sage/all__sagemath_plot.py
sage/ext_data/threejs/animation.css
sage/ext_data/threejs/animation.html
sage/ext_data/threejs/animation.js
sage/ext_data/threejs/fat_lines.js
sage/ext_data/threejs/threejs-version.txt
sage/ext_data/threejs/threejs_template.html
sage/interfaces/all__sagemath_plot.py
sage/interfaces/gnuplot.py
sage/interfaces/jmoldata.py
sage/interfaces/povray.py
sage/plot/all.py
sage/plot/animate.py
sage/plot/arc.py
sage/plot/arrow.py
sage/plot/bar_chart.py
sage/plot/bezier_path.py
sage/plot/circle.py
sage/plot/colors.py
sage/plot/complex_plot.cp312-win_amd64.pyd
sage/plot/complex_plot.pyx
sage/plot/contour_plot.py
sage/plot/density_plot.py
sage/plot/disk.py
sage/plot/ellipse.py
sage/plot/graphics.py
sage/plot/histogram.py
sage/plot/hyperbolic_arc.py
sage/plot/hyperbolic_polygon.py
sage/plot/hyperbolic_regular_polygon.py
sage/plot/line.py
sage/plot/matrix_plot.py
sage/plot/misc.py
sage/plot/multigraphics.py
sage/plot/plot.py
sage/plot/plot_field.py
sage/plot/point.py
sage/plot/polygon.py
sage/plot/primitive.py
sage/plot/scatter_plot.py
sage/plot/step.py
sage/plot/streamline_plot.py
sage/plot/text.py
sage/plot/plot3d/all.py
sage/plot/plot3d/base.cp312-win_amd64.pyd
sage/plot/plot3d/base.pxd
sage/plot/plot3d/base.pyx
sage/plot/plot3d/implicit_plot3d.py
sage/plot/plot3d/implicit_surface.cp312-win_amd64.pyd
sage/plot/plot3d/implicit_surface.pyx
sage/plot/plot3d/index_face_set.cp312-win_amd64.pyd
sage/plot/plot3d/index_face_set.pxd
sage/plot/plot3d/index_face_set.pyx
sage/plot/plot3d/introduction.py
sage/plot/plot3d/list_plot3d.py
sage/plot/plot3d/parametric_plot3d.py
sage/plot/plot3d/parametric_surface.cp312-win_amd64.pyd
sage/plot/plot3d/parametric_surface.pxd
sage/plot/plot3d/parametric_surface.pyx
sage/plot/plot3d/platonic.py
sage/plot/plot3d/plot3d.py
sage/plot/plot3d/plot_field3d.py
sage/plot/plot3d/point_c.pxi
sage/plot/plot3d/revolution_plot3d.py
sage/plot/plot3d/shapes.cp312-win_amd64.pyd
sage/plot/plot3d/shapes.pxd
passagemath_plot-10.6.47.dist-info/METADATA
passagemath_plot-10.6.47.dist-info/WHEEL
passagemath_plot-10.6.47.dist-info/top_level.txt
passagemath_plot-10.6.47.dist-info/RECORD
