Metadata-Version: 2.4
Name: passagemath-plot
Version: 10.6.47
Summary: passagemath: Plotting and graphics with Matplotlib, Three.JS, etc.
Author-email: The Sage Developers <sage-support@googlegroups.com>
Maintainer: Matthias Köppe, passagemath contributors
License-Expression: GPL-2.0-or-later
Project-URL: release notes, https://github.com/passagemath/passagemath/releases
Project-URL: repo (upstream), https://github.com/sagemath/sage
Project-URL: repo, https://github.com/passagemath/passagemath
Project-URL: documentation, https://passagemath.org/docs/latest
Project-URL: homepage (upstream), https://www.sagemath.org
Project-URL: discourse, https://passagemath.discourse.group
Project-URL: tracker (upstream), https://github.com/sagemath/sage/issues
Project-URL: tracker, https://github.com/passagemath/passagemath/issues
Classifier: Development Status :: 6 - Mature
Classifier: Intended Audience :: Education
Classifier: Intended Audience :: Science/Research
Classifier: Operating System :: POSIX
Classifier: Operating System :: POSIX :: Linux
Classifier: Operating System :: MacOS :: MacOS X
Classifier: Operating System :: Microsoft :: Windows
Classifier: Programming Language :: Python :: 3 :: Only
Classifier: Programming Language :: Python :: 3.10
Classifier: Programming Language :: Python :: 3.11
Classifier: Programming Language :: Python :: 3.12
Classifier: Programming Language :: Python :: 3.13
Classifier: Programming Language :: Python :: 3.14
Classifier: Programming Language :: Python :: Implementation :: CPython
Classifier: Topic :: Scientific/Engineering :: Mathematics
Requires-Python: <3.15,>=3.10
Requires-Dist: gmpy2~=2.1.b999
Requires-Dist: cysignals!=1.12.4; sys_platform == "win32"
Requires-Dist: cysignals!=1.12.0,>=1.11.2
Requires-Dist: memory_allocator
Requires-Dist: passagemath-categories~=10.6.47.0
Requires-Dist: passagemath-modules~=10.6.47.0
Requires-Dist: numpy>=1.19
Requires-Dist: numpy>=1.22.4
Requires-Dist: scipy>=1.5
Requires-Dist: pillow>=7.2.0
Requires-Dist: matplotlib>=3.5.1
Requires-Dist: jupyter-threejs-sage
Provides-Extra: test
Requires-Dist: passagemath-plot[tachyon]; sys_platform != "win32" and extra == "test"
Requires-Dist: passagemath-repl; extra == "test"
Provides-Extra: dot2tex
Requires-Dist: dot2tex>=2.11.3; extra == "dot2tex"
Provides-Extra: jsmol
Requires-Dist: jupyter-jsmol; extra == "jsmol"
Provides-Extra: matplotlib
Provides-Extra: playwright
Requires-Dist: playwright; extra == "playwright"
Provides-Extra: tachyon
Requires-Dist: passagemath-tachyon~=10.6.47.0; extra == "tachyon"
Provides-Extra: threejs
Provides-Extra: graphs
Requires-Dist: passagemath-graphs; extra == "graphs"
Provides-Extra: polyhedra
Requires-Dist: passagemath-polyhedra; extra == "polyhedra"
Provides-Extra: symbolics
Requires-Dist: passagemath-symbolics; extra == "symbolics"
